Metadata-Version: 1.0
Name: vinProbability
Version: 1.0
Summary: Gaussian & Binomial distributions created by VinJ
Home-page: UNKNOWN
Author: Vineet J
Author-email: UNKNOWN
License: UNKNOWN
Platform: UNKNOWN
